{
  "brand": {
    "slug": "california-s-medical",
    "name": "California's Medical",
    "productCount": 9
  },
  "products": [
    {
      "slug": "nedcann-ml-2501-moonlight",
      "name": "NEDCANN ML 25/01 Moonlight",
      "type": "flower",
      "thcPercent": 25,
      "priceMin": 789,
      "inStock": true,
      "strainName": "Moonlight"
    },
    {
      "slug": "nedcann-jh-211",
      "name": "Nedcann JH 21/01",
      "type": "flower",
      "thcPercent": 21,
      "priceMin": 773,
      "inStock": true,
      "strainName": "Jack Herer"
    },
    {
      "slug": "291-calimed-craft-no-8",
      "name": "29/01 Calimed craft No. 8",
      "type": "flower",
      "thcPercent": 29,
      "priceMin": 649,
      "inStock": true,
      "strainName": "Apples & Bananas x Jealousy"
    },
    {
      "slug": "pharma-leaves-indica-dominant-supreme-31",
      "name": "Pharma Leaves Indica Dominant Supreme 30/1",
      "type": "flower",
      "thcPercent": 29,
      "priceMin": 499,
      "inStock": true,
      "strainName": "Do-Si-Dos"
    },
    {
      "slug": "nedcann-dsd-251",
      "name": "Nedcann DSD 25/01",
      "type": "flower",
      "thcPercent": 25,
      "priceMin": 499,
      "inStock": true,
      "strainName": "Original Blitz"
    },
    {
      "slug": "california´s-medical-31-cm-craft-no-1",
      "name": "California´s Medical 30/1 CM CRAFT NO. 1",
      "type": "flower",
      "thcPercent": 30,
      "priceMin": 1065,
      "inStock": false,
      "strainName": "Scratch n Sniff"
    },
    {
      "slug": "pharma-leaves-indica-dominant-strong-211",
      "name": "Pharma Leaves Indica dominant Strong 21/1",
      "type": "flower",
      "thcPercent": 20,
      "priceMin": 395,
      "inStock": false,
      "strainName": "Do-Si-Dos"
    },
    {
      "slug": "nedcann-orb-311-moonlight",
      "name": "Nedcann ORB 31/01 Moonlight",
      "type": "flower",
      "thcPercent": 31,
      "priceMin": null,
      "inStock": false,
      "strainName": "Moonlight"
    },
    {
      "slug": "pharma-leaves-indica-dominant-strong-251",
      "name": "Pharma Leaves Indica dominant Strong 25/1",
      "type": "flower",
      "thcPercent": 25,
      "priceMin": 498,
      "inStock": false,
      "strainName": "Do-Si-Dos"
    }
  ],
  "stats": {
    "productCount": 9,
    "inStockCount": 5,
    "avgThc": 26.1,
    "priceRange": {
      "min": 395,
      "max": 1065,
      "formatted": {
        "min": "3,95 €",
        "max": "10,65 €"
      }
    }
  },
  "seo": {
    "meta": {
      "title": "California's Medical Cannabis Produkte - 9 Produkte",
      "description": "California's Medical: 9 Cannabis Produkte. 5 aktuell verfügbar. Preise vergleichen & günstig kaufen.",
      "canonical": "https://cannabisblueten.de/brand/california-s-medical",
      "robots": {
        "index": true,
        "follow": true
      },
      "openGraph": {
        "title": "California's Medical Cannabis Produkte - 9 Produkte",
        "description": "California's Medical: 9 Cannabis Produkte. 5 aktuell verfügbar. Preise vergleichen & günstig kaufen.",
        "url": "https://cannabisblueten.de/brand/california-s-medical",
        "type": "website",
        "siteName": "CannabisBlueten.de",
        "locale": "de_DE"
      }
    },
    "breadcrumbs": [
      {
        "name": "Home",
        "href": "https://cannabisblueten.de"
      },
      {
        "name": "Hersteller",
        "href": "https://cannabisblueten.de/brands"
      },
      {
        "name": "California's Medical",
        "href": "https://cannabisblueten.de/brand/california-s-medical"
      }
    ],
    "schema": [
      {
        "@context": "https://schema.org",
        "@type": "BreadcrumbList",
        "itemListElement": [
          {
            "@type": "ListItem",
            "position": 1,
            "name": "Home",
            "item": "https://cannabisblueten.de"
          },
          {
            "@type": "ListItem",
            "position": 2,
            "name": "Hersteller",
            "item": "https://cannabisblueten.de/brands"
          },
          {
            "@type": "ListItem",
            "position": 3,
            "name": "California's Medical",
            "item": "https://cannabisblueten.de/brand/california-s-medical"
          }
        ]
      },
      {
        "@context": "https://schema.org",
        "@type": "ItemList",
        "name": "California's Medical Produkte",
        "numberOfItems": 9,
        "itemListElement": [
          {
            "@type": "ListItem",
            "position": 1,
            "url": "https://cannabisblueten.de/product/nedcann-ml-2501-moonlight",
            "name": "NEDCANN ML 25/01 Moonlight"
          },
          {
            "@type": "ListItem",
            "position": 2,
            "url": "https://cannabisblueten.de/product/nedcann-jh-211",
            "name": "Nedcann JH 21/01"
          },
          {
            "@type": "ListItem",
            "position": 3,
            "url": "https://cannabisblueten.de/product/291-calimed-craft-no-8",
            "name": "29/01 Calimed craft No. 8"
          },
          {
            "@type": "ListItem",
            "position": 4,
            "url": "https://cannabisblueten.de/product/pharma-leaves-indica-dominant-supreme-31",
            "name": "Pharma Leaves Indica Dominant Supreme 30/1"
          },
          {
            "@type": "ListItem",
            "position": 5,
            "url": "https://cannabisblueten.de/product/nedcann-dsd-251",
            "name": "Nedcann DSD 25/01"
          },
          {
            "@type": "ListItem",
            "position": 6,
            "url": "https://cannabisblueten.de/product/california´s-medical-31-cm-craft-no-1",
            "name": "California´s Medical 30/1 CM CRAFT NO. 1"
          },
          {
            "@type": "ListItem",
            "position": 7,
            "url": "https://cannabisblueten.de/product/pharma-leaves-indica-dominant-strong-211",
            "name": "Pharma Leaves Indica dominant Strong 21/1"
          },
          {
            "@type": "ListItem",
            "position": 8,
            "url": "https://cannabisblueten.de/product/nedcann-orb-311-moonlight",
            "name": "Nedcann ORB 31/01 Moonlight"
          },
          {
            "@type": "ListItem",
            "position": 9,
            "url": "https://cannabisblueten.de/product/pharma-leaves-indica-dominant-strong-251",
            "name": "Pharma Leaves Indica dominant Strong 25/1"
          }
        ]
      }
    ]
  },
  "links": {
    "products": [
      {
        "href": "/product/nedcann-ml-2501-moonlight",
        "text": "NEDCANN ML 25/01 Moonlight",
        "title": "NEDCANN ML 25/01 Moonlight"
      },
      {
        "href": "/product/nedcann-jh-211",
        "text": "Nedcann JH 21/01",
        "title": "Nedcann JH 21/01"
      },
      {
        "href": "/product/291-calimed-craft-no-8",
        "text": "29/01 Calimed craft No. 8",
        "title": "29/01 Calimed craft No. 8"
      },
      {
        "href": "/product/pharma-leaves-indica-dominant-supreme-31",
        "text": "Pharma Leaves Indica Dominant Supreme 30/1",
        "title": "Pharma Leaves Indica Dominant Supreme 30/1"
      },
      {
        "href": "/product/nedcann-dsd-251",
        "text": "Nedcann DSD 25/01",
        "title": "Nedcann DSD 25/01"
      },
      {
        "href": "/product/california´s-medical-31-cm-craft-no-1",
        "text": "California´s Medical 30/1 CM CRAFT NO. 1",
        "title": "California´s Medical 30/1 CM CRAFT NO. 1"
      },
      {
        "href": "/product/pharma-leaves-indica-dominant-strong-211",
        "text": "Pharma Leaves Indica dominant Strong 21/1",
        "title": "Pharma Leaves Indica dominant Strong 21/1"
      },
      {
        "href": "/product/nedcann-orb-311-moonlight",
        "text": "Nedcann ORB 31/01 Moonlight",
        "title": "Nedcann ORB 31/01 Moonlight"
      },
      {
        "href": "/product/pharma-leaves-indica-dominant-strong-251",
        "text": "Pharma Leaves Indica dominant Strong 25/1",
        "title": "Pharma Leaves Indica dominant Strong 25/1"
      }
    ]
  }
}