{
  "strain": {
    "slug": "mac-white",
    "name": "Mac White",
    "geneticType": "hybrid",
    "thcRange": {
      "min": null,
      "max": null
    },
    "cbdRange": {
      "min": 1,
      "max": 1
    },
    "effects": [
      "Energetic",
      "Relaxed",
      "Happy"
    ],
    "tastes": [
      "Earthy",
      "Fruity",
      "Citrus",
      "Diesel"
    ],
    "terpenes": [
      "Myrcene",
      "Caryophyllene",
      "Limonene",
      "Pinene"
    ],
    "description": "Mit dem Hanf im Glück Mac White verbinden wir das Beste aus der Old School und New School der Cannabisgenetik. Wir haben die unvergleichlichen Effekte des klassischen White Widow mit dem beeindruckenden Terpenprofil und den visuellen Merkmalen des amerikanischen MAC (Miracle Alien Cookies) vereint. Diese hervorragende Kombination hat eine leicht anzubauende Hybridsorte mit leichten Sativa-Eigenschaften hervorgebracht, die sowohl Konsumenten als auch Grower mit einer beeindruckenden Menge an dicht gewachsenen, hochpotenten Buds begeistern wird.Mit einem THC-Gehalt von über 20 % und einem erdig-fruchtigen Aroma, das von Zitrus- und Dieselnoten perfekt ergänzt wird, ist Mac White besonders bei erfahrenen Cannabiskonsumenten beliebt und kann für nahezu alle Geschmäcker und Anlässe empfohlen werden.",
    "imageUrl": null
  },
  "stats": {
    "productCount": 0,
    "pharmacyCount": 0,
    "priceRange": null
  },
  "products": [],
  "similarStrains": [
    {
      "slug": "white-gorilla",
      "name": "White Gorilla",
      "geneticType": "hybrid",
      "thcMax": null
    },
    {
      "slug": "herijuana",
      "name": "Herijuana",
      "geneticType": "hybrid",
      "thcMax": null
    },
    {
      "slug": "lemon-sour-diesel",
      "name": "Lemon Sour Diesel",
      "geneticType": "hybrid",
      "thcMax": null
    },
    {
      "slug": "apple-fritter",
      "name": "Apple Fritter",
      "geneticType": "hybrid",
      "thcMax": null
    },
    {
      "slug": "spritzer",
      "name": "Spritzer",
      "geneticType": "hybrid",
      "thcMax": null
    }
  ],
  "seo": {
    "meta": {
      "title": "Mac White (Hybrid) - Wirkung, THC & Verfügbarkeit",
      "description": "Mac White: Energetic, Relaxed, Happy.",
      "canonical": "https://cannabisblueten.de/strain/mac-white",
      "robots": {
        "index": true,
        "follow": true
      },
      "openGraph": {
        "title": "Mac White (Hybrid) - Wirkung, THC & Verfügbarkeit",
        "description": "Mac White: Energetic, Relaxed, Happy.",
        "url": "https://cannabisblueten.de/strain/mac-white",
        "type": "website",
        "siteName": "CannabisBlueten.de",
        "locale": "de_DE"
      }
    },
    "breadcrumbs": [
      {
        "name": "Home",
        "href": "https://cannabisblueten.de"
      },
      {
        "name": "Sorten",
        "href": "https://cannabisblueten.de/strains"
      },
      {
        "name": "Mac White",
        "href": "https://cannabisblueten.de/strain/mac-white"
      }
    ],
    "schema": [
      {
        "@context": "https://schema.org",
        "@type": "BreadcrumbList",
        "itemListElement": [
          {
            "@type": "ListItem",
            "position": 1,
            "name": "Home",
            "item": "https://cannabisblueten.de"
          },
          {
            "@type": "ListItem",
            "position": 2,
            "name": "Sorten",
            "item": "https://cannabisblueten.de/strains"
          },
          {
            "@type": "ListItem",
            "position": 3,
            "name": "Mac White",
            "item": "https://cannabisblueten.de/strain/mac-white"
          }
        ]
      }
    ]
  },
  "links": {
    "products": [],
    "similarStrains": [
      {
        "href": "/strain/white-gorilla",
        "text": "White Gorilla",
        "title": "White Gorilla - Ähnliche Sorte"
      },
      {
        "href": "/strain/herijuana",
        "text": "Herijuana",
        "title": "Herijuana - Ähnliche Sorte"
      },
      {
        "href": "/strain/lemon-sour-diesel",
        "text": "Lemon Sour Diesel",
        "title": "Lemon Sour Diesel - Ähnliche Sorte"
      },
      {
        "href": "/strain/apple-fritter",
        "text": "Apple Fritter",
        "title": "Apple Fritter - Ähnliche Sorte"
      },
      {
        "href": "/strain/spritzer",
        "text": "Spritzer",
        "title": "Spritzer - Ähnliche Sorte"
      }
    ],
    "terpenes": [
      {
        "href": "/terpene/myrcene",
        "text": "Myrcene",
        "title": "Myrcene Terpen"
      },
      {
        "href": "/terpene/caryophyllene",
        "text": "Caryophyllene",
        "title": "Caryophyllene Terpen"
      },
      {
        "href": "/terpene/limonene",
        "text": "Limonene",
        "title": "Limonene Terpen"
      },
      {
        "href": "/terpene/pinene",
        "text": "Pinene",
        "title": "Pinene Terpen"
      }
    ]
  },
  "external": {
    "weedUrl": "https://weed.de/strains/mac-white",
    "pharmacySearchUrl": "https://weed.de/apothekensuche",
    "rezeptUrl": "https://weed.de/patient-werden"
  },
  "indexability": {
    "isIndexable": true,
    "reason": "Has data and related content"
  }
}