{
  "strain": {
    "slug": "manantiales",
    "name": "Manantiales",
    "geneticType": "hybrid",
    "thcRange": {
      "min": null,
      "max": null
    },
    "cbdRange": {
      "min": 0.1,
      "max": 0.1
    },
    "effects": [
      "Happy",
      "Relaxed",
      "Hungry",
      "Pain-relief"
    ],
    "tastes": [
      "Diesel",
      "Earthy",
      "Flowery",
      "Tangy"
    ],
    "terpenes": [
      "Limonene",
      "Linalool",
      "Beta-Caryophyllene"
    ],
    "description": "Manantiales ist eine Indica-dominante Hybridsorte, die aus der spannenden Kreuzung der fruchtigen Tangie und der preisgekrönten Kosher Kush entstanden ist. Mit einem moderaten THC-Gehalt von etwa 18 % und einem CBD-Wert von unter 0,1 % bietet sie eine solide Wirkungskraft, die das Beste aus beiden genetischen Welten vereint.\n\nDas Aromaprofil ist markant und vielschichtig. Es dominieren kräftige Noten von Diesel, die von tiefen erdigen Tönen geerdet werden. Ergänzt wird dieses robuste Bouquet durch feine blumige Akzente, die dem Ganzen eine gewisse Leichtigkeit verleihen. Das Terpenprofil, angeführt von Limonen, Linalool und Beta-Caryophyllen, ist verantwortlich für dieses charakteristische Zusammenspiel aus chemischer Tiefe, natürlicher Würze und floraler Frische.\n\nDie Wirkung wird als vorwiegend glücklich und entspannend beschrieben. Sie sorgt für eine angenehme Ruhe und ein positives Wohlbefinden, das oft von einem spürbar gesteigerten Hungergefühl begleitet wird. Aufgrund dieser beruhigenden und körperlich lösenden Eigenschaften wird Manantiales therapeutisch häufig zur Linderung von chronischen Schmerzen, Krämpfen, Entzündungen sowie Appetitlosigkeit eingesetzt.",
    "imageUrl": null
  },
  "stats": {
    "productCount": 1,
    "pharmacyCount": 0,
    "priceRange": null
  },
  "products": [
    {
      "slug": "social-choice-181-flx-mts",
      "name": "Social Choice 18/1 FLX MTS",
      "brandName": "Remexian Pharma",
      "thcPercent": 18,
      "priceMin": null,
      "inStock": false
    }
  ],
  "similarStrains": [
    {
      "slug": "frosted-cookies",
      "name": "Frosted Cookies",
      "geneticType": "hybrid",
      "thcMax": null
    },
    {
      "slug": "purple-ice-water",
      "name": "Purple Ice Water",
      "geneticType": "hybrid",
      "thcMax": null
    },
    {
      "slug": "do-si-dos",
      "name": "Do-Si-Dos",
      "geneticType": "hybrid",
      "thcMax": null
    },
    {
      "slug": "white-runtz",
      "name": "White Runtz",
      "geneticType": "hybrid",
      "thcMax": null
    },
    {
      "slug": "alien-mints",
      "name": "Alien Mints",
      "geneticType": "hybrid",
      "thcMax": null
    }
  ],
  "seo": {
    "meta": {
      "title": "Manantiales (Hybrid) - Wirkung, THC & Verfügbarkeit",
      "description": "Manantiales: Happy, Relaxed, Hungry. 1 Produkte verfügbar.",
      "canonical": "https://cannabisblueten.de/strain/manantiales",
      "robots": {
        "index": true,
        "follow": true
      },
      "openGraph": {
        "title": "Manantiales (Hybrid) - Wirkung, THC & Verfügbarkeit",
        "description": "Manantiales: Happy, Relaxed, Hungry. 1 Produkte verfügbar.",
        "url": "https://cannabisblueten.de/strain/manantiales",
        "type": "website",
        "siteName": "CannabisBlueten.de",
        "locale": "de_DE"
      }
    },
    "breadcrumbs": [
      {
        "name": "Home",
        "href": "https://cannabisblueten.de"
      },
      {
        "name": "Sorten",
        "href": "https://cannabisblueten.de/strains"
      },
      {
        "name": "Manantiales",
        "href": "https://cannabisblueten.de/strain/manantiales"
      }
    ],
    "schema": [
      {
        "@context": "https://schema.org",
        "@type": "BreadcrumbList",
        "itemListElement": [
          {
            "@type": "ListItem",
            "position": 1,
            "name": "Home",
            "item": "https://cannabisblueten.de"
          },
          {
            "@type": "ListItem",
            "position": 2,
            "name": "Sorten",
            "item": "https://cannabisblueten.de/strains"
          },
          {
            "@type": "ListItem",
            "position": 3,
            "name": "Manantiales",
            "item": "https://cannabisblueten.de/strain/manantiales"
          }
        ]
      },
      {
        "@context": "https://schema.org",
        "@type": "ItemList",
        "name": "Manantiales Produkte",
        "numberOfItems": 1,
        "itemListElement": [
          {
            "@type": "ListItem",
            "position": 1,
            "url": "https://cannabisblueten.de/product/social-choice-181-flx-mts",
            "name": "Social Choice 18/1 FLX MTS"
          }
        ]
      }
    ]
  },
  "links": {
    "products": [
      {
        "href": "/product/social-choice-181-flx-mts",
        "text": "Social Choice 18/1 FLX MTS",
        "title": "Social Choice 18/1 FLX MTS von Remexian Pharma"
      }
    ],
    "similarStrains": [
      {
        "href": "/strain/frosted-cookies",
        "text": "Frosted Cookies",
        "title": "Frosted Cookies - Ähnliche Sorte"
      },
      {
        "href": "/strain/purple-ice-water",
        "text": "Purple Ice Water",
        "title": "Purple Ice Water - Ähnliche Sorte"
      },
      {
        "href": "/strain/do-si-dos",
        "text": "Do-Si-Dos",
        "title": "Do-Si-Dos - Ähnliche Sorte"
      },
      {
        "href": "/strain/white-runtz",
        "text": "White Runtz",
        "title": "White Runtz - Ähnliche Sorte"
      },
      {
        "href": "/strain/alien-mints",
        "text": "Alien Mints",
        "title": "Alien Mints - Ähnliche Sorte"
      }
    ],
    "terpenes": [
      {
        "href": "/terpene/limonene",
        "text": "Limonene",
        "title": "Limonene Terpen"
      },
      {
        "href": "/terpene/linalool",
        "text": "Linalool",
        "title": "Linalool Terpen"
      },
      {
        "href": "/terpene/beta-caryophyllene",
        "text": "Beta-Caryophyllene",
        "title": "Beta-Caryophyllene Terpen"
      }
    ]
  },
  "indexability": {
    "isIndexable": true,
    "reason": "Has products"
  }
}