{
  "strain": {
    "slug": "sherb-headz-regular",
    "name": "Sherb HeadZ Regular",
    "geneticType": "hybrid",
    "thcRange": {
      "min": null,
      "max": null
    },
    "cbdRange": {
      "min": 1,
      "max": 1
    },
    "effects": [
      "Strong",
      "Relaxed",
      "Stimulating",
      "Euphoric"
    ],
    "tastes": [
      "Sour",
      "Diesel",
      "Sweet",
      "Citrus",
      "Tangy",
      "Earthy"
    ],
    "terpenes": [
      "Caryophyllene",
      "Limonene",
      "Myrcene"
    ],
    "description": "Sherb HeadZ Regular ist eine reguläre, ausgewogene Hybridsorte, die die süß-zitrusartige Sherbz-Mutter mit dem legendären Headbanger-Vater kombiniert. Mit einem THC-Gehalt von bis zu 27 % und einem niedrigen CBD-Anteil liefert sie eine kräftige Wirkung und ein breites Spektrum an aromatischem Ausdruck.\n\nIm Ergebnis erwartet dich ein vielschichtiger Hybrid mit süßen Z-Terpenen und Sour-/Diesel-Noten, eine intensive Terp-Kombination, die sofort auffällt. Das Terpenprofil, das von Limonen und Caryophyllen dominiert wird, enthält zusätzlich auch Myrcen, was das Aroma mit zitrusartigen, würzigen und erdigen Nuancen untermalt.\n\nDie Wirkung ist kräftig, beginnt euphorisch und geistig stimulierend, bevor die verlässliche, körperliche Entspannung des Headbanger-Erbes einsetzt. Alles in allem ist Sherb HeadZ Regular ideal für erfahrene Grower und Züchter, die intensive Terpen-Kombinationen und robuste Performance suchen.\n\n",
    "imageUrl": null
  },
  "stats": {
    "productCount": 0,
    "pharmacyCount": 0,
    "priceRange": null
  },
  "products": [],
  "similarStrains": [
    {
      "slug": "big-jack",
      "name": "Big Jack",
      "geneticType": "hybrid",
      "thcMax": null
    },
    {
      "slug": "auto-critical-dwarf",
      "name": "Auto Critical Dwarf",
      "geneticType": "hybrid",
      "thcMax": null
    },
    {
      "slug": "auto-ganja-skunk",
      "name": "Auto Ganja Skunk",
      "geneticType": "hybrid",
      "thcMax": null
    },
    {
      "slug": "auto-purple-cookies-xl",
      "name": "Auto Purple Cookies XL",
      "geneticType": "hybrid",
      "thcMax": null
    },
    {
      "slug": "auto-rainbow-belts",
      "name": "Auto Rainbow Belts",
      "geneticType": "hybrid",
      "thcMax": null
    }
  ],
  "seo": {
    "meta": {
      "title": "Sherb HeadZ Regular (Hybrid) - Wirkung, THC & Verfügbarkeit",
      "description": "Sherb HeadZ Regular: Strong, Relaxed, Stimulating.",
      "canonical": "https://cannabisblueten.de/strain/sherb-headz-regular",
      "robots": {
        "index": true,
        "follow": true
      },
      "openGraph": {
        "title": "Sherb HeadZ Regular (Hybrid) - Wirkung, THC & Verfügbarkeit",
        "description": "Sherb HeadZ Regular: Strong, Relaxed, Stimulating.",
        "url": "https://cannabisblueten.de/strain/sherb-headz-regular",
        "type": "website",
        "siteName": "CannabisBlueten.de",
        "locale": "de_DE"
      }
    },
    "breadcrumbs": [
      {
        "name": "Home",
        "href": "https://cannabisblueten.de"
      },
      {
        "name": "Sorten",
        "href": "https://cannabisblueten.de/strains"
      },
      {
        "name": "Sherb HeadZ Regular",
        "href": "https://cannabisblueten.de/strain/sherb-headz-regular"
      }
    ],
    "schema": [
      {
        "@context": "https://schema.org",
        "@type": "BreadcrumbList",
        "itemListElement": [
          {
            "@type": "ListItem",
            "position": 1,
            "name": "Home",
            "item": "https://cannabisblueten.de"
          },
          {
            "@type": "ListItem",
            "position": 2,
            "name": "Sorten",
            "item": "https://cannabisblueten.de/strains"
          },
          {
            "@type": "ListItem",
            "position": 3,
            "name": "Sherb HeadZ Regular",
            "item": "https://cannabisblueten.de/strain/sherb-headz-regular"
          }
        ]
      }
    ]
  },
  "links": {
    "products": [],
    "similarStrains": [
      {
        "href": "/strain/big-jack",
        "text": "Big Jack",
        "title": "Big Jack - Ähnliche Sorte"
      },
      {
        "href": "/strain/auto-critical-dwarf",
        "text": "Auto Critical Dwarf",
        "title": "Auto Critical Dwarf - Ähnliche Sorte"
      },
      {
        "href": "/strain/auto-ganja-skunk",
        "text": "Auto Ganja Skunk",
        "title": "Auto Ganja Skunk - Ähnliche Sorte"
      },
      {
        "href": "/strain/auto-purple-cookies-xl",
        "text": "Auto Purple Cookies XL",
        "title": "Auto Purple Cookies XL - Ähnliche Sorte"
      },
      {
        "href": "/strain/auto-rainbow-belts",
        "text": "Auto Rainbow Belts",
        "title": "Auto Rainbow Belts - Ähnliche Sorte"
      }
    ],
    "terpenes": [
      {
        "href": "/terpene/caryophyllene",
        "text": "Caryophyllene",
        "title": "Caryophyllene Terpen"
      },
      {
        "href": "/terpene/limonene",
        "text": "Limonene",
        "title": "Limonene Terpen"
      },
      {
        "href": "/terpene/myrcene",
        "text": "Myrcene",
        "title": "Myrcene Terpen"
      }
    ]
  },
  "indexability": {
    "isIndexable": true,
    "reason": "Has data and related content"
  }
}