{
  "strain": {
    "slug": "sour-cherry-punch",
    "name": "Sour Cherry Punch",
    "geneticType": "hybrid",
    "thcRange": {
      "min": null,
      "max": null
    },
    "cbdRange": {
      "min": 0.1,
      "max": 0.1
    },
    "effects": [
      "Relaxed",
      "Calming",
      "Stress-relief",
      "Pain-relief"
    ],
    "tastes": [
      "Herbal",
      "Sweet",
      "Earthy",
      "Fruity",
      "Grape",
      "Woody",
      "Sour"
    ],
    "terpenes": [
      "Linalool",
      "Myrcene",
      "Limonene",
      "Humulene",
      "Guaiol",
      "Beta-Caryophyllene"
    ],
    "description": "Sour Cherry Punch ist eine potente Indica-dominante Hybridsorte, die aus der charaktervollen Kreuzung von Sour OG Cheese und Black Cherry Punch entstanden ist. Mit einem beeindruckenden THC-Gehalt, der sich oft um die 29 % bewegt und Spitzenwerte bis 34 % erreichen kann, sowie einem CBD-Wert von unter 1 %, bietet sie eine intensive Wirkungskraft, die tiefe Entspannung mit fruchtiger Komplexität verbindet.\n\nDas Aromaprofil ist vorwiegend fruchtig und vielschichtig. Es dominieren ausgeprägte Noten von Beeren und Kirschen, die von einem Hauch Trauben begleitet werden. Ergänzt wird dieser süße Kern durch dezente Kräuterakzente, leichte Holztöne und einen säuerlichen Unterton, der dem Ganzen Tiefe verleiht. Das breite Terpenprofil, angeführt von Linalool, Myrcen, Limonen, Humulen, Guaiol und Beta-Caryophyllen, ist verantwortlich für dieses reiche Bouquet aus Fruchtsüße, säuerlicher Frische und erdiger Würze.\n\nDie Wirkung wird als stark entspannend und beruhigend beschrieben. Sie sorgt für eine umfassende körperliche Gelassenheit, die hilft, abzuschalten, und eignet sich daher besonders gut für die Anwendung in den Abendstunden. Aufgrund dieser sedierenden und stresslösenden Eigenschaften wird Sour Cherry Punch therapeutisch häufig zur Linderung von Schlaflosigkeit, chronischen Schmerzen sowie Stress eingesetzt.",
    "imageUrl": null
  },
  "stats": {
    "productCount": 3,
    "pharmacyCount": 0,
    "priceRange": {
      "min": 699,
      "max": 1299,
      "formatted": {
        "min": "6,99 €",
        "max": "12,99 €"
      }
    }
  },
  "products": [
    {
      "slug": "avaay-291-scp",
      "name": "AVAAY 29/1 SCP",
      "brandName": "Avaay",
      "thcPercent": 29,
      "priceMin": 734,
      "inStock": true
    },
    {
      "slug": "avaay-341-scp",
      "name": "avaay 34/1 SCP",
      "brandName": "Avaay",
      "thcPercent": 34,
      "priceMin": 998,
      "inStock": true
    },
    {
      "slug": "avaay-261-scp",
      "name": "avaay 26/1 SCP",
      "brandName": "Avaay",
      "thcPercent": 26,
      "priceMin": 699,
      "inStock": true
    }
  ],
  "similarStrains": [
    {
      "slug": "frosted-cookies",
      "name": "Frosted Cookies",
      "geneticType": "hybrid",
      "thcMax": null
    },
    {
      "slug": "red-velvet-cake",
      "name": "Red Velvet Cake",
      "geneticType": "hybrid",
      "thcMax": null
    },
    {
      "slug": "lx-phantasia-purp-187-sweedz",
      "name": "LX - Phantasia Purp - 187 SWEEDZ",
      "geneticType": "hybrid",
      "thcMax": null
    },
    {
      "slug": "tigerz-eye",
      "name": "Tigerz Eye",
      "geneticType": "hybrid",
      "thcMax": null
    },
    {
      "slug": "green-croc-orange",
      "name": "Green Croc Orange",
      "geneticType": "hybrid",
      "thcMax": null
    }
  ],
  "seo": {
    "meta": {
      "title": "Sour Cherry Punch (Hybrid) - Wirkung, THC & Verfügbarkeit",
      "description": "Sour Cherry Punch: Relaxed, Calming, Stress-relief. 3 Produkte verfügbar. ab 6,99 €.",
      "canonical": "https://weed.de/strain/sour-cherry-punch",
      "robots": {
        "index": true,
        "follow": true
      },
      "openGraph": {
        "title": "Sour Cherry Punch (Hybrid) - Wirkung, THC & Verfügbarkeit",
        "description": "Sour Cherry Punch: Relaxed, Calming, Stress-relief. 3 Produkte verfügbar. ab 6,99 €.",
        "url": "https://weed.de/strain/sour-cherry-punch",
        "type": "website",
        "siteName": "Weed.de",
        "locale": "de_DE"
      }
    },
    "breadcrumbs": [
      {
        "name": "Home",
        "href": "https://weed.de"
      },
      {
        "name": "Sorten",
        "href": "https://weed.de/strains"
      },
      {
        "name": "Sour Cherry Punch",
        "href": "https://weed.de/strain/sour-cherry-punch"
      }
    ],
    "schema": [
      {
        "@context": "https://schema.org",
        "@type": "BreadcrumbList",
        "itemListElement": [
          {
            "@type": "ListItem",
            "position": 1,
            "name": "Home",
            "item": "https://weed.de"
          },
          {
            "@type": "ListItem",
            "position": 2,
            "name": "Sorten",
            "item": "https://weed.de/strains"
          },
          {
            "@type": "ListItem",
            "position": 3,
            "name": "Sour Cherry Punch",
            "item": "https://weed.de/strain/sour-cherry-punch"
          }
        ]
      },
      {
        "@context": "https://schema.org",
        "@type": "ItemList",
        "name": "Sour Cherry Punch Produkte",
        "numberOfItems": 3,
        "itemListElement": [
          {
            "@type": "ListItem",
            "position": 1,
            "url": "https://weed.de/product/avaay-291-scp",
            "name": "AVAAY 29/1 SCP"
          },
          {
            "@type": "ListItem",
            "position": 2,
            "url": "https://weed.de/product/avaay-341-scp",
            "name": "avaay 34/1 SCP"
          },
          {
            "@type": "ListItem",
            "position": 3,
            "url": "https://weed.de/product/avaay-261-scp",
            "name": "avaay 26/1 SCP"
          }
        ]
      }
    ]
  },
  "links": {
    "products": [
      {
        "href": "/product/avaay-291-scp",
        "text": "AVAAY 29/1 SCP",
        "title": "AVAAY 29/1 SCP von Avaay"
      },
      {
        "href": "/product/avaay-341-scp",
        "text": "avaay 34/1 SCP",
        "title": "avaay 34/1 SCP von Avaay"
      },
      {
        "href": "/product/avaay-261-scp",
        "text": "avaay 26/1 SCP",
        "title": "avaay 26/1 SCP von Avaay"
      }
    ],
    "similarStrains": [
      {
        "href": "/strain/frosted-cookies",
        "text": "Frosted Cookies",
        "title": "Frosted Cookies - Ähnliche Sorte"
      },
      {
        "href": "/strain/red-velvet-cake",
        "text": "Red Velvet Cake",
        "title": "Red Velvet Cake - Ähnliche Sorte"
      },
      {
        "href": "/strain/lx-phantasia-purp-187-sweedz",
        "text": "LX - Phantasia Purp - 187 SWEEDZ",
        "title": "LX - Phantasia Purp - 187 SWEEDZ - Ähnliche Sorte"
      },
      {
        "href": "/strain/tigerz-eye",
        "text": "Tigerz Eye",
        "title": "Tigerz Eye - Ähnliche Sorte"
      },
      {
        "href": "/strain/green-croc-orange",
        "text": "Green Croc Orange",
        "title": "Green Croc Orange - Ähnliche Sorte"
      }
    ],
    "terpenes": [
      {
        "href": "/terpene/linalool",
        "text": "Linalool",
        "title": "Linalool Terpen"
      },
      {
        "href": "/terpene/myrcene",
        "text": "Myrcene",
        "title": "Myrcene Terpen"
      },
      {
        "href": "/terpene/limonene",
        "text": "Limonene",
        "title": "Limonene Terpen"
      },
      {
        "href": "/terpene/humulene",
        "text": "Humulene",
        "title": "Humulene Terpen"
      },
      {
        "href": "/terpene/guaiol",
        "text": "Guaiol",
        "title": "Guaiol Terpen"
      }
    ]
  },
  "indexability": {
    "isIndexable": true,
    "reason": "Has products"
  }
}