{
  "product": {
    "slug": "beacon-pk-t22",
    "name": "Beacon PK T22",
    "type": "flower",
    "genetics": "hybrid_indica",
    "thcPercent": 22,
    "cbdPercent": 1,
    "priceMin": 395,
    "priceMax": 850,
    "inStock": true,
    "pzn": [],
    "originCountry": "Kanada",
    "imageUrl": "https://weed.de/products/beacon-pk-t22-50998j.webp"
  },
  "brand": {
    "slug": "cansativa",
    "name": "Cansativa",
    "productCount": 141
  },
  "strain": {
    "slug": "pink-kush",
    "name": "Pink Kush",
    "geneticType": "indica",
    "effects": [
      "Euphoric",
      "Body-High",
      "Meditative"
    ],
    "terpenes": [
      "Myrcene",
      "Caryophyllene",
      "Limonene"
    ]
  },
  "attributes": {
    "effects": [
      "Euphoric",
      "Body-High",
      "Meditative"
    ],
    "tastes": [
      "Earthy",
      "Sweet",
      "Vanilla"
    ],
    "terpenes": [
      "Myrcene",
      "Caryophyllene",
      "Limonene"
    ]
  },
  "alternativeProducts": [
    {
      "slug": "beacon-cannabisextrakt-11",
      "name": "Beacon Cannabisextrakt 10:10",
      "brandName": "Adrexpharma",
      "thcPercent": 10,
      "priceMin": 149,
      "inStock": true
    },
    {
      "slug": "tilray-thc-18-spotlight-porto-pk",
      "name": "Tilray THC 18 Spotlight Porto PK",
      "brandName": "Tilray",
      "thcPercent": 18,
      "priceMin": 299,
      "inStock": true
    },
    {
      "slug": "enua-221-db-ca",
      "name": "enua 22/1 DB CA",
      "brandName": "enua",
      "thcPercent": 22,
      "priceMin": 369,
      "inStock": true
    },
    {
      "slug": "enua-21-db-ca",
      "name": "enua 20/1 DB CA",
      "brandName": "enua",
      "thcPercent": 20,
      "priceMin": 397,
      "inStock": true
    },
    {
      "slug": "canify-cannabis-flos-231-pt-ku-pk",
      "name": "Canify Cannabis flos 23/1 PT Ku. PK",
      "brandName": "Canify",
      "thcPercent": 23,
      "priceMin": 399,
      "inStock": true
    },
    {
      "slug": "wellford-aquaponic-231-pik",
      "name": "Wellford Aquaponic 23/1 PIK",
      "brandName": "Therismos",
      "thcPercent": 23,
      "priceMin": 485,
      "inStock": true
    }
  ],
  "seo": {
    "meta": {
      "title": "Beacon PK T22 - Cansativa | ab 3,95 €",
      "description": "Beacon PK T22 von Cansativa. THC: 22%, CBD: 1%. Sorte: Pink Kush. Preis ab 3,95 €. Jetzt verfügbar.",
      "canonical": "https://cannabisblueten.de/product/beacon-pk-t22",
      "robots": {
        "index": true,
        "follow": true
      },
      "openGraph": {
        "title": "Beacon PK T22 - Cansativa | ab 3,95 €",
        "description": "Beacon PK T22 von Cansativa. THC: 22%, CBD: 1%. Sorte: Pink Kush. Preis ab 3,95 €. Jetzt verfügbar.",
        "url": "https://cannabisblueten.de/product/beacon-pk-t22",
        "type": "product",
        "siteName": "CannabisBlueten.de",
        "locale": "de_DE",
        "image": "https://weed.de/products/beacon-pk-t22-50998j.webp"
      }
    },
    "breadcrumbs": [
      {
        "name": "Home",
        "href": "https://cannabisblueten.de"
      },
      {
        "name": "Produkte",
        "href": "https://cannabisblueten.de/products"
      },
      {
        "name": "Cansativa",
        "href": "https://cannabisblueten.de/brand/cansativa"
      },
      {
        "name": "Beacon PK T22",
        "href": "https://cannabisblueten.de/product/beacon-pk-t22"
      }
    ],
    "schema": [
      {
        "@context": "https://schema.org",
        "@type": "BreadcrumbList",
        "itemListElement": [
          {
            "@type": "ListItem",
            "position": 1,
            "name": "Home",
            "item": "https://cannabisblueten.de"
          },
          {
            "@type": "ListItem",
            "position": 2,
            "name": "Produkte",
            "item": "https://cannabisblueten.de/products"
          },
          {
            "@type": "ListItem",
            "position": 3,
            "name": "Beacon PK T22",
            "item": "https://cannabisblueten.de/product/beacon-pk-t22"
          }
        ]
      },
      {
        "@context": "https://schema.org",
        "@type": "Product",
        "name": "Beacon PK T22",
        "url": "https://cannabisblueten.de/product/beacon-pk-t22",
        "brand": {
          "@type": "Brand",
          "name": "Cansativa"
        },
        "gtin13": [],
        "sku": [],
        "description": "Medizinisches Cannabis Produkt. THC: 22%, CBD: 1%, Genetik: hybrid_indica",
        "category": "Medizinisches Cannabis",
        "offers": {
          "@type": "Offer",
          "url": "https://cannabisblueten.de/product/beacon-pk-t22",
          "priceCurrency": "EUR",
          "price": "3.95",
          "availability": "https://schema.org/InStock",
          "itemCondition": "https://schema.org/NewCondition",
          "priceSpecification": {
            "@type": "PriceSpecification",
            "minPrice": "3.95",
            "maxPrice": "8.50",
            "priceCurrency": "EUR"
          }
        }
      }
    ]
  },
  "links": {
    "strain": {
      "href": "/strain/pink-kush",
      "text": "Pink Kush",
      "title": "Pink Kush Sorte"
    },
    "brand": {
      "href": "/brand/cansativa",
      "text": "Cansativa",
      "title": "Alle Cansativa Produkte"
    },
    "alternatives": [
      {
        "href": "/product/beacon-cannabisextrakt-11",
        "text": "Beacon Cannabisextrakt 10:10",
        "title": "Alternative: Beacon Cannabisextrakt 10:10"
      },
      {
        "href": "/product/tilray-thc-18-spotlight-porto-pk",
        "text": "Tilray THC 18 Spotlight Porto PK",
        "title": "Alternative: Tilray THC 18 Spotlight Porto PK"
      },
      {
        "href": "/product/enua-221-db-ca",
        "text": "enua 22/1 DB CA",
        "title": "Alternative: enua 22/1 DB CA"
      },
      {
        "href": "/product/enua-21-db-ca",
        "text": "enua 20/1 DB CA",
        "title": "Alternative: enua 20/1 DB CA"
      },
      {
        "href": "/product/canify-cannabis-flos-231-pt-ku-pk",
        "text": "Canify Cannabis flos 23/1 PT Ku. PK",
        "title": "Alternative: Canify Cannabis flos 23/1 PT Ku. PK"
      },
      {
        "href": "/product/wellford-aquaponic-231-pik",
        "text": "Wellford Aquaponic 23/1 PIK",
        "title": "Alternative: Wellford Aquaponic 23/1 PIK"
      }
    ]
  },
  "external": {
    "weedUrl": "https://weed.de/produkt/beacon-pk-t22",
    "pharmacySearchUrl": "https://weed.de/apothekensuche",
    "rezeptUrl": "https://weed.de/patient-werden"
  },
  "indexability": {
    "isIndexable": true,
    "reason": "In stock"
  }
}