{
  "product": {
    "slug": "cannamedical-indica-classic-cr",
    "name": "Cannamedical Indica classic CR",
    "type": "flower",
    "genetics": "indica",
    "thcPercent": 20,
    "cbdPercent": 1,
    "priceMin": 476,
    "priceMax": 699,
    "inStock": true,
    "pzn": null,
    "originCountry": "N/A",
    "imageUrl": "https://weed.de/products/cannamedical-indica-classic-cr-f82f37.png"
  },
  "brand": {
    "slug": "cannamedical",
    "name": "Cannamedical",
    "productCount": 238
  },
  "strain": {
    "slug": "crazy-runtz",
    "name": "Crazy Runtz",
    "geneticType": "hybrid",
    "effects": [
      "Relaxed",
      "Happy",
      "Hungry"
    ],
    "terpenes": [
      "Caryophyllene"
    ]
  },
  "attributes": {
    "effects": [
      "Relaxed",
      "Happy",
      "Hungry"
    ],
    "tastes": [
      "Fruity",
      "Sweet",
      "Earthy"
    ],
    "terpenes": [
      "Caryophyllene"
    ]
  },
  "alternativeProducts": [
    {
      "slug": "aurora-thc-25-cannabis-extract",
      "name": "Aurora THC 25 Cannabis Extract",
      "brandName": "Cansativa",
      "thcPercent": 2.5,
      "priceMin": 397,
      "inStock": true
    },
    {
      "slug": "adven-cannabisextrakt-thc-10-cbd-10",
      "name": "Adven Cannabisextrakt THC 10 CBD 10",
      "brandName": "Adven",
      "thcPercent": 10,
      "priceMin": 560,
      "inStock": true
    },
    {
      "slug": "cannamedical-indica-forte-ma",
      "name": "Cannamedical Indica forte MA CR",
      "brandName": "Cannamedical",
      "thcPercent": 24,
      "priceMin": 595,
      "inStock": true
    },
    {
      "slug": "cannamedical-indica-forte-ej",
      "name": "Cannamedical Indica forte EJ",
      "brandName": "Cannamedical",
      "thcPercent": 24,
      "priceMin": 678,
      "inStock": true
    },
    {
      "slug": "demecan-typ-1",
      "name": "Demecan Typ 1",
      "brandName": "Demecan",
      "thcPercent": 21,
      "priceMin": 694,
      "inStock": true
    },
    {
      "slug": "251vayamed-cannabisextrakt",
      "name": "25/1Vayamed Cannabisextrakt",
      "brandName": "Vayamed",
      "thcPercent": 2.5,
      "priceMin": 824,
      "inStock": true
    }
  ],
  "seo": {
    "meta": {
      "title": "Cannamedical Indica classic CR | ab 4,76 €",
      "description": "Cannamedical Indica classic CR von Cannamedical. THC: 20%, CBD: 1%. Sorte: Crazy Runtz. Preis ab 4,76 €. Jetzt verfügbar.",
      "canonical": "https://cannabisblueten.de/product/cannamedical-indica-classic-cr",
      "robots": {
        "index": true,
        "follow": true
      },
      "openGraph": {
        "title": "Cannamedical Indica classic CR | ab 4,76 €",
        "description": "Cannamedical Indica classic CR von Cannamedical. THC: 20%, CBD: 1%. Sorte: Crazy Runtz. Preis ab 4,76 €. Jetzt verfügbar.",
        "url": "https://cannabisblueten.de/product/cannamedical-indica-classic-cr",
        "type": "product",
        "siteName": "CannabisBlueten.de",
        "locale": "de_DE",
        "image": "https://weed.de/products/cannamedical-indica-classic-cr-f82f37.png"
      }
    },
    "breadcrumbs": [
      {
        "name": "Home",
        "href": "https://cannabisblueten.de"
      },
      {
        "name": "Produkte",
        "href": "https://cannabisblueten.de/products"
      },
      {
        "name": "Cannamedical",
        "href": "https://cannabisblueten.de/brand/cannamedical"
      },
      {
        "name": "Cannamedical Indica classic CR",
        "href": "https://cannabisblueten.de/product/cannamedical-indica-classic-cr"
      }
    ],
    "schema": [
      {
        "@context": "https://schema.org",
        "@type": "BreadcrumbList",
        "itemListElement": [
          {
            "@type": "ListItem",
            "position": 1,
            "name": "Home",
            "item": "https://cannabisblueten.de"
          },
          {
            "@type": "ListItem",
            "position": 2,
            "name": "Produkte",
            "item": "https://cannabisblueten.de/products"
          },
          {
            "@type": "ListItem",
            "position": 3,
            "name": "Cannamedical Indica classic CR",
            "item": "https://cannabisblueten.de/product/cannamedical-indica-classic-cr"
          }
        ]
      },
      {
        "@context": "https://schema.org",
        "@type": "Product",
        "name": "Cannamedical Indica classic CR",
        "url": "https://cannabisblueten.de/product/cannamedical-indica-classic-cr",
        "brand": {
          "@type": "Brand",
          "name": "Cannamedical"
        },
        "description": "Medizinisches Cannabis Produkt. THC: 20%, CBD: 1%, Genetik: indica",
        "category": "Medizinisches Cannabis",
        "offers": {
          "@type": "Offer",
          "url": "https://cannabisblueten.de/product/cannamedical-indica-classic-cr",
          "priceCurrency": "EUR",
          "price": "4.76",
          "availability": "https://schema.org/InStock",
          "itemCondition": "https://schema.org/NewCondition",
          "priceSpecification": {
            "@type": "PriceSpecification",
            "minPrice": "4.76",
            "maxPrice": "6.99",
            "priceCurrency": "EUR"
          }
        }
      }
    ]
  },
  "links": {
    "strain": {
      "href": "/strain/crazy-runtz",
      "text": "Crazy Runtz",
      "title": "Crazy Runtz Sorte"
    },
    "brand": {
      "href": "/brand/cannamedical",
      "text": "Cannamedical",
      "title": "Alle Cannamedical Produkte"
    },
    "alternatives": [
      {
        "href": "/product/aurora-thc-25-cannabis-extract",
        "text": "Aurora THC 25 Cannabis Extract",
        "title": "Alternative: Aurora THC 25 Cannabis Extract"
      },
      {
        "href": "/product/adven-cannabisextrakt-thc-10-cbd-10",
        "text": "Adven Cannabisextrakt THC 10 CBD 10",
        "title": "Alternative: Adven Cannabisextrakt THC 10 CBD 10"
      },
      {
        "href": "/product/cannamedical-indica-forte-ma",
        "text": "Cannamedical Indica forte MA CR",
        "title": "Alternative: Cannamedical Indica forte MA CR"
      },
      {
        "href": "/product/cannamedical-indica-forte-ej",
        "text": "Cannamedical Indica forte EJ",
        "title": "Alternative: Cannamedical Indica forte EJ"
      },
      {
        "href": "/product/demecan-typ-1",
        "text": "Demecan Typ 1",
        "title": "Alternative: Demecan Typ 1"
      },
      {
        "href": "/product/251vayamed-cannabisextrakt",
        "text": "25/1Vayamed Cannabisextrakt",
        "title": "Alternative: 25/1Vayamed Cannabisextrakt"
      }
    ]
  },
  "indexability": {
    "isIndexable": true,
    "reason": "In stock"
  }
}